{"name":"Can Login","id":"login;can-login","testSteps":[{"number":1,"description":"Given I go to login page","duration":9,"startTime":"2022-09-27T17:28:12.058203800+07:00[Asia/Bangkok]","result":"SUCCESS","precondition":false,"level":0},{"number":2,"description":"When I input valid email or phone","duration":14,"startTime":"2022-09-27T17:28:12.070172100+07:00[Asia/Bangkok]","result":"SUCCESS","precondition":false,"level":0},{"number":3,"description":"And I input valid password","duration":18,"startTime":"2022-09-27T17:28:12.089122500+07:00[Asia/Bangkok]","result":"SUCCESS","precondition":false,"level":0},{"number":4,"description":"And I click Login button","duration":6,"startTime":"2022-09-27T17:28:12.110064500+07:00[Asia/Bangkok]","result":"SUCCESS","precondition":false,"level":0},{"number":5,"description":"Then I go to home page","duration":4,"startTime":"2022-09-27T17:28:12.123032200+07:00[Asia/Bangkok]","result":"SUCCESS","precondition":false,"level":0}],"userStory":{"id":"login","storyName":"Login","path":"file:src/test/resources/features/User/login.feature","narrative":"  As a user\n  I want to login in Linkedin\n  So I can access a features in LinkedIn","type":"feature"},"featureTag":{"name":"User/Login","type":"feature","displayName":"User/Login"},"title":"Can Login","tags":[{"name":"User/Login","type":"feature","displayName":"Login"},{"name":"User","type":"capability","displayName":"User"}],"startTime":"2022-09-27T17:28:12.038256600+07:00[Asia/Bangkok]","duration":91,"projectKey":"","isManualTestingUpToDate":false,"manual":false,"testSource":"Cucumber","result":"SUCCESS"}